anticrlf/__init__.py
anticrlf/exception.py
anticrlf/types.py
anticrlf/tests/__init__.py
anticrlf/tests/test_formatter.py
anticrlf/tests/test_substitutionmap.py
logging_formatter_anticrlf-1.2.1.dist-info/LICENSE
logging_formatter_anticrlf-1.2.1.dist-info/METADATA
logging_formatter_anticrlf-1.2.1.dist-info/WHEEL
logging_formatter_anticrlf-1.2.1.dist-info/top_level.txt
logging_formatter_anticrlf-1.2.1.dist-info/RECORD
