Metadata-Version: 2.1
Name: logging-formatter-anticrlf
Version: 1.2.1
Summary: Python logging Formatter for CRLF Injection (CWE-93 / CWE-117) prevention
Home-page: https://github.com/darrenpmeyer/logging-formatter-anticrlf
Author: Darren P Meyer
Author-email: Darren P Meyer <darren@darrenpmeyer.com>
License: BSD-2-clause
Project-URL: home, https://github.com/darrenpmeyer/logging-formatter-anticrlf
License-File: LICENSE
Provides-Extra: dev
Requires-Dist: tox >=3.8.0 ; extra == 'dev'
Requires-Dist: pytest ; extra == 'dev'
